{
    "name": "polish_cv",
    "language": "Polish",
    "dialect": null,
    "maintainer": "[Vox Communis](https://osf.io/t957v/)",
    "license_link": "[CC-0](https://creativecommons.org/publicdomain/zero/1.0/)",
    "phone_set": "CV",
    "phones": "a b d d\u0361z d\u0361\u0291 f i j k k\u02b2 l m n p q r s t t\u0361s t\u0361\u0255 u v w x z \u00fc \u014b \u0161 \u0254 \u0254\u0303 \u0255 \u025b \u025b\u0303 \u0261 \u0261\u02b2 \u0268 \u0272 \u0282 \u0290 \u0291",
    "word_count": 53062,
    "train_date": "2022-02-03",
    "version": "2.0.0",
    "citation": "@misc{Ahn_Chodroff_2022, author={Ahn, Emily and Chodroff, Eleanor}, title={VoxCommunis Corpus}, address={\\url{https://osf.io/t957v}, publisher={OSF}, year={2022}, month={Jan}}"
}
