{
    "name": "swedish_mfa",
    "language": "Swedish",
    "dialect": "",
    "maintainer": "[Montreal Forced Aligner](https://montreal-forced-aligner.readthedocs.io/)",
    "license_link": "[CC BY 4.0](https://github.com/MontrealCorpusTools/mfa-models/tree/main/dictionary/swedish/mfa/v3.0.0/LICENSE)",
    "license": "CC BY 4.0",
    "phone_set": "MFA",
    "phones": [
        "a",
        "a˥˧",
        "a˥˩",
        "a˧˩",
        "a˩",
        "b",
        "d̪",
        "eː",
        "eː˥˧",
        "eː˥˩",
        "eː˧˩",
        "eː˩",
        "f",
        "h",
        "iː",
        "iː˥˧",
        "iː˥˩",
        "iː˧˩",
        "j",
        "k",
        "kʰ",
        "l̪",
        "m",
        "n̪",
        "oː",
        "oː˥˧",
        "oː˥˩",
        "oː˧˩",
        "p",
        "pʰ",
        "r",
        "s̪",
        "t̪",
        "t̪ʰ",
        "uː",
        "uː˥˧",
        "uː˥˩",
        "uː˧˩",
        "yː",
        "yː˥˧",
        "yː˥˩",
        "yː˧˩",
        "yː˩",
        "øː",
        "øː˥˧",
        "øː˥˩",
        "øː˧˩",
        "øː˩",
        "ŋ",
        "œ",
        "œ˥˩",
        "œ˧˩",
        "ɑː",
        "ɑː˥˧",
        "ɑː˥˩",
        "ɑː˧˩",
        "ɔ",
        "ɔ˥˧",
        "ɔ˥˩",
        "ɔ˧˩",
        "ɔ˩",
        "ɕ",
        "ɖ",
        "ɛ",
        "ɛː",
        "ɛː˥˧",
        "ɛː˥˩",
        "ɛː˧˩",
        "ɛ˥˧",
        "ɛ˥˩",
        "ɛ˧˩",
        "ɛ˩",
        "ɡ",
        "ɧ",
        "ɪ",
        "ɪ˥˧",
        "ɪ˥˩",
        "ɪ˧˩",
        "ɪ˩",
        "ɭ",
        "ɳ",
        "ɵ",
        "ɵ˥˧",
        "ɵ˥˩",
        "ɵ˧˩",
        "ɵ˩",
        "ʂ",
        "ʈ",
        "ʈʰ",
        "ʉː",
        "ʉː˥˧",
        "ʉː˥˩",
        "ʉː˧˩",
        "ʊ",
        "ʊ˥˩",
        "ʊ˧˩",
        "ʊ˩",
        "ʋ",
        "ʏ",
        "ʏ˥˧",
        "ʏ˥˩",
        "ʏ˧˩",
        "ʏ˩"
    ],
    "word_count": 49655,
    "train_date": "2024-03-18",
    "version": "3.0.0",
    "citation": "@techreport{mfa_swedish_mfa_dictionary_2024,\n\tauthor={McAuliffe, Michael and Sonderegger, Morgan},\n\ttitle={Swedish MFA dictionary v3.0.0},\n\taddress={\\url{https://mfa-models.readthedocs.io/pronunciation dictionary/Swedish/Swedish MFA dictionary v3_0_0.html}},\n\tyear={2024},\n\tmonth={Mar},\n}"
}
